vargrest/VERSION.txt
vargrest/__init__.py
vargrest/__main__.py
vargrest/api.py
vargrest/auxiliary/__init__.py
vargrest/auxiliary/box.py
vargrest/auxiliary/curvefit.py
vargrest/auxiliary/ellipses.py
vargrest/auxiliary/geometry.py
vargrest/auxiliary/progress.py
vargrest/auxiliary/sliceplot.py
vargrest/auxiliary/variogram.py
vargrest/auxiliary/variogramplot.py
vargrest/auxiliary/visualization.py
vargrest/variogramdata/__init__.py
vargrest/variogramdata/_utilities.py
vargrest/variogramdata/variogramdata.py
vargrest/variogramestimation/__init__.py
vargrest/variogramestimation/empiricalvariogram.py
vargrest/variogramestimation/parametricvariogram.py
vargrest/variogramestimation/variogramestimation.py
vargrest/variogramresults/__init__.py
vargrest/variogramresults/summary.py
vargrest-1.0.dist-info/LICENSE
vargrest-1.0.dist-info/METADATA
vargrest-1.0.dist-info/WHEEL
vargrest-1.0.dist-info/top_level.txt
vargrest-1.0.dist-info/RECORD
